{
  "$schema": "https://developer-docs.flowable.com/schemas/palette.json",
  "Palette-Id": "flowable-frontend-palette",
  "patchPalettes": [
    "flowable-work-form-palette",
    "flowable-work-page-palette"
  ],
  "resourceBundles": [
    "com/flowable/config/custom/palette/training-i18n"
  ],
  "groups": {
    "training": {
      "index": 1
    }
  },
  "presentations": [
    {
      "id": "hello-world.presentation",
      "bigIcon": "component-presentations/palette-icons/hello-world.svg",
      "icon": "component-presentations/palette-icons/hello-world.svg"
    }
  ],
  "stencils": [
    {
      "id": "hello-world",
      "xmlTag": "trainingHelloworld",
      "title": "Hello World",
      "description": "Custom greeting component with optional label",
      "viewPath": "component-presentations/editor-views/htmlComponent.svg",
      "superId": "Component",
      "presentationId": "hello-world.presentation",
      "groups": [
        "training"
      ],
      "propertyPackages": [
        "labelWithDefaultValueAttributes"
      ],
      "properties": [
        {
          "id": "value",
          "visible": false
        },
        {
          "id": "default-value",
          "visible": false
        },
        {
          "id": "locationToGreet",
          "title": "Location to Greet",
          "value": "World",
          "category": "details",
          "type": "SimpleTextExpression",
          "path": "extraSettings.locationToGreet",
          "runtime": true,
          "index": 10
        }
      ]
    }
  ]
}

